beautybook/__init__.py
beautybook/__version__.py
beautybook/core.py
beautybook-0.1.2.dist-info/METADATA
beautybook-0.1.2.dist-info/WHEEL
beautybook-0.1.2.dist-info/top_level.txt
beautybook-0.1.2.dist-info/RECORD
