Metadata-Version: 2.4
Name: beautybook
Version: 0.1.2
Summary: A Dynamic Table Visualization Tool for Iterative Processes
Author-email: Abolfazl Mohammadpour <Mohampouraz@gmail.com>
License: MIT
Project-URL: Homepage, https://pypi.org/project/beautybook/
Project-URL: Repository, https://github.com/mohampouraz/iutils/
Project-URL: Documentation, https://github.com/mohampouraz/iutils/#readme
Project-URL: BugTracker, https://github.com/mohampouraz/iutils/issues
Keywords: Python,Jupyter,notebook,Colab,Data Visualization,Table,IPython,MLOps
Classifier: Programming Language :: Python :: 3
Classifier: Programming Language :: Python :: 3 :: Only
Classifier: Development Status :: 5 - Production/Stable
Classifier: License :: OSI Approved :: MIT License
Classifier: Intended Audience :: Developers
Classifier: Topic :: Software Development :: Libraries
Classifier: Framework :: Jupyter
Requires-Python: >=3.8
